.isort.cfg
CHANGES.rst
LICENSE
MANIFEST.in
Makefile
README.rst
buildout.cfg
ci.cfg
requirements.txt
setup.cfg
setup.py
src/collective/__init__.py
src/collective.eeafaceted.batchactions.egg-info/PKG-INFO
src/collective.eeafaceted.batchactions.egg-info/SOURCES.txt
src/collective.eeafaceted.batchactions.egg-info/dependency_links.txt
src/collective.eeafaceted.batchactions.egg-info/entry_points.txt
src/collective.eeafaceted.batchactions.egg-info/namespace_packages.txt
src/collective.eeafaceted.batchactions.egg-info/not-zip-safe
src/collective.eeafaceted.batchactions.egg-info/requires.txt
src/collective.eeafaceted.batchactions.egg-info/top_level.txt
src/collective/eeafaceted/__init__.py
src/collective/eeafaceted/batchactions/__init__.py
src/collective/eeafaceted/batchactions/columns.zcml
src/collective/eeafaceted/batchactions/configure.zcml
src/collective/eeafaceted/batchactions/interfaces.py
src/collective/eeafaceted/batchactions/mk_sync_locales.sh
src/collective/eeafaceted/batchactions/setuphandlers.py
src/collective/eeafaceted/batchactions/testing.py
src/collective/eeafaceted/batchactions/testing.zcml
src/collective/eeafaceted/batchactions/upgrades.zcml
src/collective/eeafaceted/batchactions/utils.py
src/collective/eeafaceted/batchactions/browser/__init__.py
src/collective/eeafaceted/batchactions/browser/configure.zcml
src/collective/eeafaceted/batchactions/browser/viewlets.py
src/collective/eeafaceted/batchactions/browser/views.py
src/collective/eeafaceted/batchactions/browser/overrides/.gitkeep
src/collective/eeafaceted/batchactions/browser/static/.gitkeep
src/collective/eeafaceted/batchactions/browser/static/batch_actions.css
src/collective/eeafaceted/batchactions/browser/static/batch_actions.js
src/collective/eeafaceted/batchactions/browser/templates/batch_actions_viewlet.pt
src/collective/eeafaceted/batchactions/locales/collective.eeafaceted.batchactions.pot
src/collective/eeafaceted/batchactions/locales/manual.pot
src/collective/eeafaceted/batchactions/locales/en/LC_MESSAGES/collective.eeafaceted.batchactions.po
src/collective/eeafaceted/batchactions/locales/fr/LC_MESSAGES/collective.eeafaceted.batchactions.po
src/collective/eeafaceted/batchactions/profiles/default/collectiveeeafacetedbatchactions_marker.txt
src/collective/eeafaceted/batchactions/profiles/default/cssregistry.xml
src/collective/eeafaceted/batchactions/profiles/default/jsregistry.xml
src/collective/eeafaceted/batchactions/profiles/default/metadata.xml
