Metadata-Version: 2.4
Name: collective.eeafaceted.batchactions
Version: 1.16.6
Summary: This package provides batch actions for eea.facetednavigation dashboard
Home-page: https://github.com/IMIO/collective.eeafaceted.batchactions
Download-URL: https://pypi.org/project/collective.eeafaceted.batchactions
Author: IMIO
Author-email: dev@imio.be
License: GPL V2
Keywords: faceted navigation batch actions table
Classifier: Development Status :: 5 - Production/Stable
Classifier: Environment :: Web Environment
Classifier: Framework :: Plone :: 4.3
Classifier: Framework :: Plone :: 5.0
Classifier: Framework :: Plone :: 5.1
Classifier: License :: OSI Approved :: GNU General Public License v2 (GPLv2)
Classifier: Operating System :: OS Independent
Classifier: Programming Language :: Python :: 2.7
License-File: LICENSE
Requires-Dist: Plone
Requires-Dist: setuptools
Requires-Dist: collective.eeafaceted.z3ctable>=2.0
Requires-Dist: imio.helpers
Requires-Dist: imio.pyutils
Requires-Dist: plone.formwidget.masterselect<2.0.0
Provides-Extra: test
Requires-Dist: plone.app.dexterity; extra == "test"
Requires-Dist: plone.app.testing; extra == "test"
Requires-Dist: plone.app.relationfield; extra == "test"
Requires-Dist: plone.app.robotframework; extra == "test"
Requires-Dist: collective.contact.core>1.43.0; extra == "test"
Requires-Dist: ftw.labels>1.3.1; extra == "test"
Provides-Extra: develop
Requires-Dist: zest.releaser; extra == "develop"
Dynamic: author
Dynamic: author-email
Dynamic: classifier
Dynamic: description
Dynamic: download-url
Dynamic: home-page
Dynamic: keywords
Dynamic: license
Dynamic: license-file
Dynamic: provides-extra
Dynamic: requires-dist
Dynamic: summary
